[
  {
    "name": "minScore",
    "expected": 0.9,
    "actual": 0.59,
    "values": [
      0.58,
      0.59,
      0.59
    ],
    "operator": ">=",
    "passed": false,
    "auditProperty": "performance",
    "auditId": "categories",
    "level": "error",
    "url": "http://localhost:3000/"
  },
  {
    "name": "maxNumericValue",
    "expected": 2500,
    "actual": 4915.4392000000025,
    "values": [
      4915.4392000000025,
      4922.3503,
      4919.855299999999
    ],
    "operator": "<=",
    "passed": false,
    "auditId": "largest-contentful-paint",
    "level": "error",
    "url": "http://localhost:3000/",
    "auditTitle": "Largest Contentful Paint",
    "auditDocumentationLink": "https://developer.chrome.com/docs/lighthouse/performance/lighthouse-largest-contentful-paint/"
  },
  {
    "name": "maxNumericValue",
    "expected": 0.1,
    "actual": 0.6572811634275275,
    "values": [
      0.6572811634275275,
      0.6572830783414011,
      0.6572830783414011
    ],
    "operator": "<=",
    "passed": false,
    "auditId": "cumulative-layout-shift",
    "level": "error",
    "url": "http://localhost:3000/",
    "auditTitle": "Cumulative Layout Shift",
    "auditDocumentationLink": "https://web.dev/articles/cls"
  }
]